Metadata-Version: 2.0
Name: odoo8-addon-analytic-base-department
Version: 8.0.1.0.0
Summary: Analytic Department Categorization
Home-page: http://camptocamp.com
Author: UNKNOWN
Author-email: UNKNOWN
License: AGPL-3
Platform: UNKNOWN
Requires-Dist: odoo (<9.0a,>=8.0a)
Classifier: Programming Language :: Python :: 2.7
Classifier: Framework :: Odoo
Classifier: License :: OSI Approved :: GNU Affero General Public License v3
